w300/__init__.py
w300/w300.py
ALS_123222-0.1.dist-info/LICENSE
ALS_123222-0.1.dist-info/METADATA
ALS_123222-0.1.dist-info/WHEEL
ALS_123222-0.1.dist-info/top_level.txt
ALS_123222-0.1.dist-info/RECORD
