Metadata-Version: 2.1
Name: ALS-123222
Version: 0.1
Summary: project
Home-page: https://github.com/106062132/ALS
Author: Edward
Author-email: myth594@gmail.com
License: MIT
Platform: UNKNOWN
